MANIFEST.in
README.txt
setup.py
repoze/__init__.py
repoze.what.plugins.couchdbkit.egg-info/PKG-INFO
repoze.what.plugins.couchdbkit.egg-info/SOURCES.txt
repoze.what.plugins.couchdbkit.egg-info/dependency_links.txt
repoze.what.plugins.couchdbkit.egg-info/entry_points.txt
repoze.what.plugins.couchdbkit.egg-info/namespace_packages.txt
repoze.what.plugins.couchdbkit.egg-info/not-zip-safe
repoze.what.plugins.couchdbkit.egg-info/requires.txt
repoze.what.plugins.couchdbkit.egg-info/top_level.txt
repoze/what/__init__.py
repoze/what/plugins/__init__.py
repoze/what/plugins/couchdbkit/__init__.py
repoze/what/plugins/couchdbkit/basic.py
repoze/what/plugins/couchdbkit/documents.py
repoze/what/plugins/couchdbkit/tests.py
repoze/what/plugins/couchdbkit/_design/auth/views/group_by_name/map.js
repoze/what/plugins/couchdbkit/_design/auth/views/group_users/map.js
repoze/what/plugins/couchdbkit/_design/auth/views/user_by_name/map.js