Metadata-Version: 1.0
Name: repoze.what.plugins.couchdbkit
Version: 0.2
Summary: repoze.what plugin for couchdbkit
Home-page: http://www.gawel.org/repoze.what.plugins.couchdbkit/index.html
Author: Gael Pasgrimaud
Author-email: gael@gawel.org
License: MIT
Keywords: wsgi auth repoze what couchdb
Platform: UNKNOWN
Classifier: Intended Audience :: Developers
Classifier: License :: OSI Approved :: MIT License
Classifier: Topic :: Internet :: WWW/HTTP :: WSGI :: Middleware
